actserpt/__init__.py
actserpt/main.py
actserpt-0.0.1.dist-info/METADATA
actserpt-0.0.1.dist-info/WHEEL
actserpt-0.0.1.dist-info/RECORD
