Metadata-Version: 2.1
Name: actserpt
Version: 0.0.1
Summary: Creating files for Pyhton.
License: arass0101
Keywords: example,library
Author: Aras Kuzey SULTAR
Author-email: teknobilimmail@gmail.com
Requires-Python: >=3.6,<4.0
Classifier: License :: Other/Proprietary License
Classifier: Programming Language :: Python :: 3
Classifier: Programming Language :: Python :: 3.6
Classifier: Programming Language :: Python :: 3.7
Classifier: Programming Language :: Python :: 3.8
Classifier: Programming Language :: Python :: 3.9
Classifier: Programming Language :: Python :: 3.10
Classifier: Programming Language :: Python :: 3.11
Classifier: Programming Language :: Python :: 3.12
